{
  "tags" : [ "java", "generics", "casting" ],
  "comments" : [ {
    "owner" : {
      "account_id" : 957496,
      "reputation" : 7301,
      "user_id" : 982542,
      "user_type" : "registered",
      "accept_rate" : 80,
      "profile_image" : "https://www.gravatar.com/avatar/407012e5e5a0498c8c2dfe6c186bde27?s=256&d=identicon&r=PG",
      "display_name" : "ThanksForAllTheFish",
      "link" : "https://stackoverflow.com/users/982542/thanksforallthefish"
    },
    "edited" : false,
    "score" : 0,
    "creation_date" : 1359127257,
    "post_id" : 14524751,
    "comment_id" : 20252377,
    "content_license" : "CC BY-SA 3.0",
    "body" : "why the last one should print <code>null</code>? and, why don&#39;t you return an <code>Object</code>? Java erasure will anyway translate your generic into an <code>Object</code>, so why don&#39;t you write directly <code>public static Object convertInstanceOfObject</code>?"
  }, {
    "owner" : {
      "account_id" : 307137,
      "reputation" : 3576,
      "user_id" : 618279,
      "user_type" : "registered",
      "accept_rate" : 76,
      "profile_image" : "https://www.gravatar.com/avatar/de60c73bb43d7dca8d32035722f9b7c7?s=256&d=identicon&r=PG",
      "display_name" : "sedran",
      "link" : "https://stackoverflow.com/users/618279/sedran"
    },
    "reply_to_user" : {
      "account_id" : 957496,
      "reputation" : 7301,
      "user_id" : 982542,
      "user_type" : "registered",
      "accept_rate" : 80,
      "profile_image" : "https://www.gravatar.com/avatar/407012e5e5a0498c8c2dfe6c186bde27?s=256&d=identicon&r=PG",
      "display_name" : "ThanksForAllTheFish",
      "link" : "https://stackoverflow.com/users/982542/thanksforallthefish"
    },
    "edited" : false,
    "score" : 0,
    "creation_date" : 1359128261,
    "post_id" : 14524751,
    "comment_id" : 20252681,
    "content_license" : "CC BY-SA 3.0",
    "body" : "I can decide the later one later, but I wanted to catch ClassCastException :) The thing I wanted to know is that an object is an instance of another object before casting, where I don&#39;t know its actual type."
  } ],
  "answers" : [ {
    "comments" : [ {
      "owner" : {
        "account_id" : 40221,
        "reputation" : 32465,
        "user_id" : 116509,
        "user_type" : "registered",
        "accept_rate" : 100,
        "profile_image" : "https://i.sstatic.net/GsYqn.jpg?s=256",
        "display_name" : "artbristol",
        "link" : "https://stackoverflow.com/users/116509/artbristol"
      },
      "edited" : false,
      "score" : 75,
      "creation_date" : 1359131902,
      "post_id" : 14524815,
      "comment_id" : 20254776,
      "content_license" : "CC BY-SA 3.0",
      "body" : "I know it&#39;s from the OP, but really <code>{ catch(ClassCastException e) {   return null;    }</code> is unforgiveable"
    }, {
      "owner" : {
        "account_id" : 181832,
        "reputation" : 1865,
        "user_id" : 416104,
        "user_type" : "registered",
        "accept_rate" : 61,
        "profile_image" : "https://i.sstatic.net/rDhUG.jpg?s=256",
        "display_name" : "Cristiano",
        "link" : "https://stackoverflow.com/users/416104/cristiano"
      },
      "edited" : false,
      "score" : 1,
      "creation_date" : 1466078978,
      "post_id" : 14524815,
      "comment_id" : 63174834,
      "content_license" : "CC BY-SA 3.0",
      "body" : "@SpaceTrucker, thanks. I&#39;m wondering, would be any way to use .isArray() inside convertInstanceOfObject() in the someObject and extract the class (as the intArrayType) from it by reflection and then call an internal private method passing those? But even doing this, I must to create an empty array and pass it in the public method, right?"
    }, {
      "owner" : {
        "account_id" : 335050,
        "reputation" : 324,
        "user_id" : 661902,
        "user_type" : "registered",
        "profile_image" : "https://www.gravatar.com/avatar/874857c9cd846b1dbea91d27de102526?s=256&d=identicon&r=PG",
        "display_name" : "Antonio Malcolm",
        "link" : "https://stackoverflow.com/users/661902/antonio-malcolm"
      },
      "edited" : false,
      "score" : 5,
      "creation_date" : 1472186181,
      "post_id" : 14524815,
      "comment_id" : 65660171,
      "content_license" : "CC BY-SA 3.0",
      "body" : "It should be mentioned that type erasure actually happens at compilation, not runtime."
    } ],
    "owner" : {
      "account_id" : 1580843,
      "reputation" : 13696,
      "user_id" : 1466267,
      "user_type" : "registered",
      "accept_rate" : 91,
      "profile_image" : "https://www.gravatar.com/avatar/c47d1f7544a8c4a1bb7a41d511f53604?s=256&d=identicon&r=PG",
      "display_name" : "SpaceTrucker",
      "link" : "https://stackoverflow.com/users/1466267/spacetrucker"
    },
    "is_accepted" : true,
    "score" : 279,
    "last_activity_date" : 1519911131,
    "last_edit_date" : 1519911131,
    "creation_date" : 1359127192,
    "answer_id" : 14524815,
    "question_id" : 14524751,
    "content_license" : "CC BY-SA 3.0",
    "body" : "<p>You have to use a <code>Class</code> instance because of the generic type erasure during compilation.</p>\n\n<pre><code>public static &lt;T&gt; T convertInstanceOfObject(Object o, Class&lt;T&gt; clazz) {\n    try {\n        return clazz.cast(o);\n    } catch(ClassCastException e) {\n        return null;\n    }\n}\n</code></pre>\n\n<p>The declaration of <a href=\"http://docs.oracle.com/javase/1.5.0/docs/api/java/lang/Class.html#cast%28java.lang.Object%29\" rel=\"noreferrer\">that method</a> is:</p>\n\n<pre><code>public T cast(Object o)\n</code></pre>\n\n<p>This can also be used for array types. It would look like this:</p>\n\n<pre><code>final Class&lt;int[]&gt; intArrayType = int[].class;\nfinal Object someObject = new int[]{1,2,3};\nfinal int[] instance = convertInstanceOfObject(someObject, intArrayType);\n</code></pre>\n\n<p>Note that when <code>someObject</code> is passed to <code>convertToInstanceOfObject</code> it has the compile time type <code>Object</code>.</p>\n"
  }, {
    "comments" : [ {
      "owner" : {
        "account_id" : 16113213,
        "reputation" : 68,
        "user_id" : 11630974,
        "user_type" : "registered",
        "profile_image" : "https://i.sstatic.net/mNn78.jpg?s=256",
        "display_name" : "Silverlight777",
        "link" : "https://stackoverflow.com/users/11630974/silverlight777"
      },
      "edited" : false,
      "score" : 0,
      "creation_date" : 1743620647,
      "post_id" : 44323160,
      "comment_id" : 140291817,
      "content_license" : "CC BY-SA 4.0",
      "body" : "Trying to clarify why this happens: Because of erasure Java skips the cast to T (which is just Object at runtime, so cast is useless), so <code>345435.34</code> remains Double."
    } ],
    "owner" : {
      "account_id" : 12090,
      "reputation" : 10508,
      "user_id" : 23637,
      "user_type" : "registered",
      "accept_rate" : 83,
      "profile_image" : "https://www.gravatar.com/avatar/5b55e7c59c71312dfaf37162915f6f4e?s=256&d=identicon&r=PG",
      "display_name" : "Alvin",
      "link" : "https://stackoverflow.com/users/23637/alvin"
    },
    "is_accepted" : false,
    "score" : 29,
    "last_activity_date" : 1496388404,
    "creation_date" : 1496388404,
    "answer_id" : 44323160,
    "question_id" : 14524751,
    "content_license" : "CC BY-SA 3.0",
    "body" : "<p>I stumble upon this question and it grabbed my interest. The accepted answer is completely correct, but I thought I do provide my findings at JVM byte code level to explain why the OP encounter the <code>ClassCastException</code>.</p>\n\n<p>I have the code which is pretty much the same as OP's code: </p>\n\n<pre><code>public static &lt;T&gt; T convertInstanceOfObject(Object o) {\n    try {\n       return (T) o;\n    } catch (ClassCastException e) {\n        return null;\n    }\n}\n\npublic static void main(String[] args) {\n    String k = convertInstanceOfObject(345435.34);\n    System.out.println(k);\n}\n</code></pre>\n\n<p>and the corresponding byte code is:</p>\n\n<pre><code>public static &lt;T&gt; T convertInstanceOfObject(java.lang.Object);\n    Code:\n       0: aload_0\n       1: areturn\n       2: astore_1\n       3: aconst_null\n       4: areturn\n    Exception table:\n       from    to  target type\n           0     1     2   Class java/lang/ClassCastException\n\n  public static void main(java.lang.String[]);\n    Code:\n       0: ldc2_w        #3                  // double 345435.34d\n       3: invokestatic  #5                  // Method java/lang/Double.valueOf:(D)Ljava/lang/Double;\n       6: invokestatic  #6                  // Method convertInstanceOfObject:(Ljava/lang/Object;)Ljava/lang/Object;\n       9: checkcast     #7                  // class java/lang/String\n      12: astore_1\n      13: getstatic     #8                  // Field java/lang/System.out:Ljava/io/PrintStream;\n      16: aload_1\n      17: invokevirtual #9                  // Method java/io/PrintStream.println:(Ljava/lang/String;)V\n      20: return\n</code></pre>\n\n<p>Notice that <code>checkcast</code> byte code instruction happens in the main method not the <code>convertInstanceOfObject</code> and <code>convertInstanceOfObject</code> method does not have any instruction that can throw <code>ClassCastException</code>. Because the main method does not catch the <code>ClassCastException</code> hence when you execute the main method you will get a <code>ClassCastException</code> and not the expectation of printing <code>null</code>.</p>\n\n<p>Now I modify the code to the accepted answer:</p>\n\n<pre><code>public static &lt;T&gt; T convertInstanceOfObject(Object o, Class&lt;T&gt; clazz) {\n        try {\n            return clazz.cast(o);\n        } catch (ClassCastException e) {\n            return null;\n        }\n    }\n    public static void main(String[] args) {\n        String k = convertInstanceOfObject(345435.34, String.class);\n        System.out.println(k);\n    }\n</code></pre>\n\n<p>The corresponding byte code is:</p>\n\n<pre><code>public static &lt;T&gt; T convertInstanceOfObject(java.lang.Object, java.lang.Class&lt;T&gt;);\n    Code:\n       0: aload_1\n       1: aload_0\n       2: invokevirtual #2                  // Method java/lang/Class.cast:(Ljava/lang/Object;)Ljava/lang/Object;\n       5: areturn\n       6: astore_2\n       7: aconst_null\n       8: areturn\n    Exception table:\n       from    to  target type\n           0     5     6   Class java/lang/ClassCastException\n\n  public static void main(java.lang.String[]);\n    Code:\n       0: ldc2_w        #4                  // double 345435.34d\n       3: invokestatic  #6                  // Method java/lang/Double.valueOf:(D)Ljava/lang/Double;\n       6: ldc           #7                  // class java/lang/String\n       8: invokestatic  #8                  // Method convertInstanceOfObject:(Ljava/lang/Object;Ljava/lang/Class;)Ljava/lang/Object;\n      11: checkcast     #7                  // class java/lang/String\n      14: astore_1\n      15: getstatic     #9                  // Field java/lang/System.out:Ljava/io/PrintStream;\n      18: aload_1\n      19: invokevirtual #10                 // Method java/io/PrintStream.println:(Ljava/lang/String;)V\n      22: return\n</code></pre>\n\n<p>Notice that there is an <code>invokevirtual</code> instruction in the <code>convertInstanceOfObject</code> method that calls <code>Class.cast()</code> method which throws <code>ClassCastException</code> which will be catch by the <code>catch(ClassCastException e)</code> bock and return <code>null</code>; hence, \"null\" is printed to console without any exception.</p>\n"
  }, {
    "comments" : [ {
      "owner" : {
        "account_id" : 7028,
        "reputation" : 1088,
        "user_id" : 12002,
        "user_type" : "registered",
        "profile_image" : "https://www.gravatar.com/avatar/0a8af18977c123e06d2e94a06be4fc2c?s=256&d=identicon&r=PG",
        "display_name" : "haslo",
        "link" : "https://stackoverflow.com/users/12002/haslo"
      },
      "edited" : false,
      "score" : 1,
      "creation_date" : 1564739416,
      "post_id" : 51078769,
      "comment_id" : 101138260,
      "content_license" : "CC BY-SA 4.0",
      "body" : "Much better. I hate exception-based program flows.  In my case, I wanted to check whether the object in question implements an interface. For that, I used <code>isAssignableFrom</code>."
    }, {
      "owner" : {
        "account_id" : 305679,
        "reputation" : 1366,
        "user_id" : 615987,
        "user_type" : "registered",
        "profile_image" : "https://www.gravatar.com/avatar/86f9f14c9c3022a3bd91fa0082ee00d6?s=256&d=identicon&r=PG",
        "display_name" : "Patrick",
        "link" : "https://stackoverflow.com/users/615987/patrick"
      },
      "edited" : false,
      "score" : 0,
      "creation_date" : 1617707483,
      "post_id" : 51078769,
      "comment_id" : 118373679,
      "content_license" : "CC BY-SA 4.0",
      "body" : "Why not add a type bound to the generic argument instead? <code>public static &lt;T extends Foo&gt; T cast(....)</code> instead of checking whether it is a <code>Foo</code>"
    }, {
      "owner" : {
        "account_id" : 8104679,
        "reputation" : 1924,
        "user_id" : 6106641,
        "user_type" : "registered",
        "accept_rate" : 80,
        "profile_image" : "https://www.gravatar.com/avatar/abcf76142302a63f68d274623802104f?s=256&d=identicon&r=PG&f=y&so-version=2",
        "display_name" : "Archmede",
        "link" : "https://stackoverflow.com/users/6106641/archmede"
      },
      "edited" : false,
      "score" : 1,
      "creation_date" : 1698355101,
      "post_id" : 51078769,
      "comment_id" : 136398647,
      "content_license" : "CC BY-SA 4.0",
      "body" : "Aren&#39;t exception based flows better than passing nulls around? @intra"
    } ],
    "owner" : {
      "account_id" : 1170480,
      "reputation" : 735,
      "user_id" : 1147785,
      "user_type" : "registered",
      "profile_image" : "https://www.gravatar.com/avatar/4ce67da9f635955db043c4ad3bf80208?s=256&d=identicon&r=PG",
      "display_name" : "intra",
      "link" : "https://stackoverflow.com/users/1147785/intra"
    },
    "is_accepted" : false,
    "score" : 26,
    "last_activity_date" : 1530176507,
    "creation_date" : 1530176507,
    "answer_id" : 51078769,
    "question_id" : 14524751,
    "content_license" : "CC BY-SA 4.0",
    "body" : "<p>If you do not want to depend on throwing exception (which you probably should not) you can try this:</p>\n\n<pre><code>public static &lt;T&gt; T cast(Object o, Class&lt;T&gt; clazz) {\n    return clazz.isInstance(o) ? clazz.cast(o) : null;\n}\n</code></pre>\n"
  } ],
  "owner" : {
    "account_id" : 307137,
    "reputation" : 3576,
    "user_id" : 618279,
    "user_type" : "registered",
    "accept_rate" : 76,
    "profile_image" : "https://www.gravatar.com/avatar/de60c73bb43d7dca8d32035722f9b7c7?s=256&d=identicon&r=PG",
    "display_name" : "sedran",
    "link" : "https://stackoverflow.com/users/618279/sedran"
  },
  "is_answered" : true,
  "view_count" : 321552,
  "accepted_answer_id" : 14524815,
  "answer_count" : 3,
  "score" : 185,
  "last_activity_date" : 1752389717,
  "creation_date" : 1359127014,
  "last_edit_date" : 1752389717,
  "question_id" : 14524751,
  "link" : "https://stackoverflow.com/questions/14524751/cast-object-to-generic-type-for-returning",
  "title" : "Cast Object to Generic Type for returning",
  "body" : "<p>Is there a way to cast an object to return value of a method?\nI tried this way but it gave a compile time error in &quot;instanceof&quot; part:</p>\n<pre><code>public static &lt;T&gt; T convertInstanceOfObject(Object o) {\n    if (o instanceof T) {\n        return (T) o;\n    } else {\n        return null;\n    }\n}\n</code></pre>\n<p>I also tried this one but it gave a runtime exception, ClassCastException:</p>\n<pre><code>public static &lt;T&gt; T convertInstanceOfObject(Object o) {\n    try {\n        T rv = (T)o;\n        return rv;\n    } catch(java.lang.ClassCastException e) {\n        return null;\n    }\n}\n</code></pre>\n<p>Is there a possible way of doing this easily:</p>\n<pre><code>String s = convertInstanceOfObject(&quot;string&quot;);\nSystem.out.println(s); // should print &quot;string&quot;\nInteger i = convertInstanceOfObject(4);\nSystem.out.println(i); // should print &quot;4&quot;\nString k = convertInstanceOfObject(345435.34);\nSystem.out.println(k); // should print &quot;null&quot;\n</code></pre>\n<p>EDIT: I wrote a working copy of the correct answer:</p>\n<pre><code>public static &lt;T&gt; T convertInstanceOfObject(Object o, Class&lt;T&gt; clazz) {\n    try {\n        return clazz.cast(o);\n    } catch(ClassCastException e) {\n        return null;\n    }\n}\n\npublic static void main(String args[]) {\n    String s = convertInstanceOfObject(&quot;string&quot;, String.class);\n    System.out.println(s);\n    Integer i = convertInstanceOfObject(4, Integer.class);\n    System.out.println(i);\n    String k = convertInstanceOfObject(345435.34, String.class);\n    System.out.println(k);\n}\n</code></pre>\n"
}